Metadata-Version: 1.1
Name: pyrclib
Version: 0.2.6
Summary: Python IRC bot framework
Home-page: https://github.com/martinsileno/pyrclib
Author: Martin Sileno
Author-email: martin@1way.it
License: MIT
Platform: UNKNOWN
Classifier: Intended Audience :: Developers
Classifier: Programming Language :: Python
Classifier: Topic :: Software Development :: Libraries :: Python Modules
